xmrig/__init__.py
xmrig/xmrig.py
xmrig-1.1.2.dist-info/LICENSE
xmrig-1.1.2.dist-info/METADATA
xmrig-1.1.2.dist-info/WHEEL
xmrig-1.1.2.dist-info/RECORD
