Metadata-Version: 2.1
Name: xmrig
Version: 1.1.2
Summary: A python package for easy in line interfacing with XMRig Miner HTTP API
Author: CoulterStutz
Author-email: coultercash@gmail.com
Requires-Python: >=3.9,<4.0
Classifier: Programming Language :: Python :: 3
Classifier: Programming Language :: Python :: 3.9
Classifier: Programming Language :: Python :: 3.10
Classifier: Programming Language :: Python :: 3.11
Classifier: Programming Language :: Python :: 3.12
Classifier: Programming Language :: Python :: 3.13
Requires-Dist: requests (>=2.32.3,<3.0.0)
